eventflowsys/__init__.py
eventflowsys/logger_Injectable.py
eventflowsys/bus/__init__.py
eventflowsys/bus/async_bus.py
eventflowsys/bus/base_bus.py
eventflowsys/bus/thread_bus.py
eventflowsys-0.1.4.dist-info/METADATA
eventflowsys-0.1.4.dist-info/WHEEL
eventflowsys-0.1.4.dist-info/top_level.txt
eventflowsys-0.1.4.dist-info/RECORD
