Metadata-Version: 2.4
Name: eventflowsys
Version: 0.1.4
Summary: Base logger and internal event bus implementations.
Author: Your Name
Requires-Python: >=3.8
Requires-Dist: loguru>=0.7.3
Provides-Extra: dev
Requires-Dist: pytest; extra == "dev"
Requires-Dist: pytest-asyncio; extra == "dev"
